CHANGES.rst
MANIFEST.in
README.rst
setup.py
src/text_based_switcher/__init__.py
src/text_based_switcher/__main__.py
src/text_based_switcher.egg-info/PKG-INFO
src/text_based_switcher.egg-info/SOURCES.txt
src/text_based_switcher.egg-info/dependency_links.txt
src/text_based_switcher.egg-info/entry_points.txt
src/text_based_switcher.egg-info/not-zip-safe
src/text_based_switcher.egg-info/pbr.json
src/text_based_switcher.egg-info/requires.txt
src/text_based_switcher.egg-info/top_level.txt