Metadata-Version: 1.1
Name: text-based-switcher
Version: 0.0.2.dev0
Summary: Text-based window switcher for Unity
Home-page: http://pypi.python.org/pypi/text-based-switcher
Author: Jean Jordaan
Author-email: jean.jordaan@gmail.com
License: GPLv3
Keywords: ubuntu unity switcher
Platform: UNKNOWN
Classifier: Programming Language :: Python
Classifier: Environment :: X11 Applications
Classifier: Environment :: Plugins
Classifier: Intended Audience :: End Users/Desktop
Classifier: Topic :: Desktop Environment :: Window Managers
Classifier: License :: OSI Approved :: GNU General Public License v3 (GPLv3)
